{
  "hash": "93b02acc027cba9f96654ebc2dd83045",
  "result": {
    "markdown": "---\ntitle: Shaemus\nhuman: Casey Tisdale, MLS\ndescription: |\n  I adopted him from a humane society as a treat for getting into graduate school. I’ve had him for two years and we’ve been best friends since.\nquote: |\n  Shaemus really loves cuddles and attention\nimage: featured.jpg\ncategories: Mini schnauzer, chihuahua and terrier mix\ntalent: |\n  He can dance, bow, and play dead\nhabit: |\n  Lying on my laptop\ntitle-block-categories: false\ntitle-block-banner: false\ntitle-block-style: none\n---\n\n\n::: grid\n::: {#about-pet-text .g-col-12 .g-col-md-6}\n![](featured.jpg){.lightbox}\n:::\n\n::: {.g-col-12 .g-col-md-6}\n::: {simple-info}\n# Meet {{< meta title >}}\n\n### Quote: \n\n> {{< meta quote >}}\n\n### Breed:\n\n\n{{< meta categories >}}\n\n\n\n### Bad Habit:\n\n\n{{< meta habit >}}\n\n\n\n### Special Talent:\n\n\n{{< meta talent >}}\n\n\n:::\n:::\n:::\n\n##### Submitted by: {{< meta human >}}\n\n## Bio\n\n\n{{< meta description >}}\n\n\n\n## Gallery\n\n\n::: {.cell}\n::: {.cell-output-display}\n![](index_files/figure-html/pet gallery-1.png){width=1200}\n:::\n:::",
    "supporting": [
      "index_files"
    ],
    "filters": [
      "rmarkdown/pagebreak.lua"
    ],
    "includes": {},
    "engineDependencies": {},
    "preserve": {},
    "postProcess": true
  }
}